adaptive_trend_analysis/__init__.py
adaptive_trend_analysis/trend_analyzer.py
adaptive_trend_analysis-0.1.2.dist-info/LICENSE
adaptive_trend_analysis-0.1.2.dist-info/METADATA
adaptive_trend_analysis-0.1.2.dist-info/WHEEL
adaptive_trend_analysis-0.1.2.dist-info/top_level.txt
adaptive_trend_analysis-0.1.2.dist-info/RECORD
