Metadata-Version: 2.2
Name: adaptive_trend_analysis
Version: 0.1.2
Summary: A library for Gradient-Adaptive Smoothing (GAS) trend analysis.
Home-page: https://github.com/yourusername/adaptive_trend_analysis
Author: Jherson Aguto
Author-email: dalisayfernando4@gmail.com
Classifier: Programming Language :: Python :: 3
Classifier: License :: OSI Approved :: MIT License
Classifier: Operating System :: OS Independent
Requires-Python: >=3.6
License-File: LICENSE
Requires-Dist: numpy
Requires-Dist: pandas
Dynamic: author
Dynamic: author-email
Dynamic: classifier
Dynamic: home-page
Dynamic: requires-dist
Dynamic: requires-python
Dynamic: summary
